{
    "CFG": {
        "BRANCH": "master-wr",
        "CACHE": "config/index-cache/layers_wrs_com",
        "DESCRIPTION": "Wind River Developer Layer Index",
        "TYPE": "restapi-web",
        "URL": "http://layers.wrs.com/layerindex/api/"
    },
    "branches": [
        {
            "bitbake_branch": "wr-10.18-20180806",
            "id": 38,
            "name": "master-wr",
            "short_description": "Wind River Linux Development",
            "sort_priority": 1,
            "update_environment": null,
            "updated": "2018-08-06T03:08:00+0000",
            "updates_enabled": true
        }
    ],
    "distros": [],
    "layerBranches": [
        {
            "actual_branch": "wr-10.18-20180806",
            "branch": 38,
            "collection": "core",
            "id": 14953,
            "layer": 1,
            "updated": "2018-08-08T02:08:46+0000",
            "vcs_last_commit": "2018-08-08T02:08:46+0000",
            "vcs_last_fetch": "2018-08-08T02:08:46+0000",
            "vcs_last_rev": "29d4b1147ee098af895ab8144642aedfc5c491a8",
            "vcs_subdir": "meta",
            "version": "11",
            "yp_compatible_version": null
        },
        {
            "actual_branch": "wr-10.18-20180726",
            "branch": 38,
            "collection": "cube",
            "id": 833857,
            "layer": 246,
            "updated": "2018-08-06T18:08:14+0000",
            "vcs_last_commit": "2018-08-06T18:08:14+0000",
            "vcs_last_fetch": "2018-08-06T18:08:14+0000",
            "vcs_last_rev": "679de0e798963b04c4408d1b3a677380159a790d",
            "vcs_subdir": "meta-cube",
            "version": "1",
            "yp_compatible_version": null
        },
        {
            "actual_branch": "wr-10.18-20180726",
            "branch": 38,
            "collection": "metagw",
            "id": 833859,
            "layer": 248,
            "updated": "2018-08-06T18:08:28+0000",
            "vcs_last_commit": "2018-08-06T18:08:28+0000",
            "vcs_last_fetch": "2018-08-06T18:08:28+0000",
            "vcs_last_rev": "b5ad56c6eca698f7d537a25622892866edef2801",
            "vcs_subdir": "",
            "version": null,
            "yp_compatible_version": null
        }
    ],
    "layerDependencies": [
        {
            "dependency": 1,
            "id": 40754,
            "layerbranch": 833859,
            "required": true
        },
        {
            "dependency": 246,
            "id": 40755,
            "layerbranch": 833859,
            "required": true
        }
    ],
    "layerItems": [
        {
            "classic": false,
            "description": "OpenEmbedded-Core is a layer containing the core metadata for current versions\r\nof OpenEmbedded. It is distro-less (can build a functional image with\r\nDISTRO = \"nodistro\") and contains only emulated machine support.",
            "id": 1,
            "index_preference": 1000,
            "layer_type": "A",
            "mailing_list_url": "",
            "name": "openembedded-core",
            "status": "P",
            "summary": "Core Metadata",
            "updated": "2018-05-30T18:05:28+0000",
            "usage_url": "README",
            "vcs_url": "#BASE_URL#/oe-core",
            "vcs_web_commit_url": "",
            "vcs_web_file_base_url": "",
            "vcs_web_tree_base_url": "",
            "vcs_web_url": ""
        },
        {
            "classic": false,
            "description": "Recipe changes for OverC related cubes (containers)",
            "id": 246,
            "index_preference": 0,
            "layer_type": "S",
            "mailing_list_url": "",
            "name": "meta-cube",
            "status": "P",
            "summary": "Recipe changes for OverC related cubes (containers)",
            "updated": "2018-08-06T18:08:24+0000",
            "usage_url": "",
            "vcs_url": "#BASE_URL#/meta-overc",
            "vcs_web_commit_url": "http://lxgit.wrs.com/cgit/layers/meta-overc/commit/id=%hash%",
            "vcs_web_file_base_url": "",
            "vcs_web_tree_base_url": "",
            "vcs_web_url": ""
        },
        {
            "classic": false,
            "description": "The goal of this layer is to extend the meta-overc in such a way as to\r\nadd additional middleware which is useful on a internet gateway\r\nplatform.  This layer will not work properly without meta-overc and\r\nmeta-cube.",
            "id": 248,
            "index_preference": 0,
            "layer_type": "S",
            "mailing_list_url": "",
            "name": "meta-gateway",
            "status": "P",
            "summary": "extend the meta-overc with additional middleware as an internet gateway",
            "updated": "2018-08-06T18:08:37+0000",
            "usage_url": "",
            "vcs_url": "#BASE_URL#/meta-gateway",
            "vcs_web_commit_url": "http://lxgit.wrs.com/cgit/layers/meta-gateway/commit/id=%hash%",
            "vcs_web_file_base_url": "",
            "vcs_web_tree_base_url": "",
            "vcs_web_url": ""
        }
    ],
    "machines": [],
    "recipes": [
        {
            "bbclassextend": "",
            "blacklisted": "",
            "bugtracker": "",
            "description": "OpenWrt MBIM modem utility",
            "filename": "umbim_git.bb",
            "filepath": "recipes-connectivity/umbim",
            "homepage": "http://git.openwrt.org/?p=project/umbim.git;a=summary",
            "id": 682631,
            "inherits": "cmake pkgconfig",
            "layerbranch": 833859,
            "license": "GPL-2.0",
            "pn": "umbim",
            "provides": "umbim ",
            "pv": "git",
            "section": "base",
            "summary": "",
            "updated": "2018-08-06T22:08:21+0000"
        },
        {
            "bbclassextend": "",
            "blacklisted": "",
            "bugtracker": "",
            "description": "",
            "filename": "wireless-tools_30.pre9.bb",
            "filepath": "recipes-connectivity/wireless-tools",
            "homepage": "https://hewlettpackard.github.io/wireless-tools/Tools.html",
            "id": 682632,
            "inherits": "",
            "layerbranch": 833859,
            "license": "GPLv2 & (LGPLv2.1 | MPL-1.1 | BSD)",
            "pn": "wireless-tools",
            "provides": "wireless-tools ",
            "pv": "30.pre9",
            "section": "base",
            "summary": "Tools for the Linux Standard Wireless Extension Subsystem",
            "updated": "2018-08-06T22:08:21+0000"
        },
        {
            "bbclassextend": "",
            "blacklisted": "",
            "bugtracker": "",
            "description": "OpenWrt uqmi utility",
            "filename": "uqmi_git.bb",
            "filepath": "recipes-connectivity/uqmi",
            "homepage": "http://git.openwrt.org/?p=project/uqmi.git;a=summary",
            "id": 682633,
            "inherits": "cmake pkgconfig",
            "layerbranch": 833859,
            "license": "GPL-2.0",
            "pn": "uqmi",
            "provides": "uqmi ",
            "pv": "git",
            "section": "base",
            "summary": "",
            "updated": "2018-08-06T22:08:21+0000"
        },
        {
            "bbclassextend": "",
            "blacklisted": "",
            "bugtracker": "",
            "description": "Comgt is a command line tool for controlling, configuring and interacting with Option Wireless 3G and 2G ( HSDPA, UMTS, EDGE, GPRS, GSM) data devices within the Linux environment.",
            "filename": "comgt_0.32.bb",
            "filepath": "recipes-connectivity/comgt",
            "homepage": "",
            "id": 682634,
            "inherits": "",
            "layerbranch": 833859,
            "license": "GPLv2",
            "pn": "comgt",
            "provides": "comgt ",
            "pv": "0.32",
            "section": "console/utils",
            "summary": "Option/Vodafone 3G/GPRS control tool",
            "updated": "2018-08-06T22:08:21+0000"
        },
        {
            "bbclassextend": "",
            "blacklisted": "",
            "bugtracker": "",
            "description": "Mosquitto is an open source (BSD licensed) message broker that implements the MQ Telemetry Transport protocol version 3.1. MQTT provides a lightweight method of carrying out messaging using a publish/subscribe model. ",
            "filename": "mosquitto_1.4.10.bb",
            "filepath": "recipes-connectivity/mosquitto",
            "homepage": "http://mosquitto.org/",
            "id": 682635,
            "inherits": "systemd",
            "layerbranch": 833859,
            "license": "BSD",
            "pn": "mosquitto",
            "provides": "mosquitto ",
            "pv": "1.4.10",
            "section": "console/network",
            "summary": "Open source MQTT v3.1 implemention",
            "updated": "2018-08-06T22:08:21+0000"
        },
        {
            "bbclassextend": "",
            "blacklisted": "",
            "bugtracker": "",
            "description": "This package provide Wind River gateway bootup services.",
            "filename": "gw-boot_1.0.bb",
            "filepath": "recipes-core-luci/gw-boot",
            "homepage": "",
            "id": 682636,
            "inherits": "systemd",
            "layerbranch": 833859,
            "license": "windriver",
            "pn": "gw-boot",
            "provides": "gw-boot ",
            "pv": "1.0",
            "section": "base",
            "summary": "",
            "updated": "2018-08-06T22:08:21+0000"
        },
        {
            "bbclassextend": "",
            "blacklisted": "",
            "bugtracker": "",
            "description": "The abbreviation UCI stands for Unified Configuration Interface and is intended to centralize the whole configuration of your project. Configuring should be easy, more straight forward.",
            "filename": "uci_git.bb",
            "filepath": "recipes-core-luci/uci",
            "homepage": "http://wiki.openwrt.org/doc/uci",
            "id": 682637,
            "inherits": "cmake",
            "layerbranch": 833859,
            "license": "GPLv2 & LGPLv2.1+",
            "pn": "uci",
            "provides": "uci ",
            "pv": "git",
            "section": "console/utils",
            "summary": "UCI is the successor of the nvram based configuration found in the White Russian series of OpenWrt.",
            "updated": "2018-08-06T22:08:22+0000"
        },
        {
            "bbclassextend": "native",
            "blacklisted": "",
            "bugtracker": "",
            "description": "Lua is a powerful light-weight programming language designed for extending applications.",
            "filename": "lua_5.1.5.bb",
            "filepath": "recipes-core-luci/lua",
            "homepage": "http://www.lua.org/",
            "id": 682638,
            "inherits": "binconfig pkgconfig",
            "layerbranch": 833859,
            "license": "MIT",
            "pn": "lua",
            "provides": "lua ",
            "pv": "5.1.5",
            "section": "base",
            "summary": "",
            "updated": "2018-08-06T22:08:22+0000"
        },
        {
            "bbclassextend": "",
            "blacklisted": "",
            "bugtracker": "",
            "description": "Networking extension library for Lua",
            "filename": "luasocket_git.bb",
            "filepath": "recipes-core-luci/luasocket",
            "homepage": "https://github.com/diegonehab/luasocket",
            "id": 682639,
            "inherits": "",
            "layerbranch": 833859,
            "license": "MIT",
            "pn": "luasocket",
            "provides": "luasocket ",
            "pv": "git",
            "section": "base",
            "summary": "",
            "updated": "2018-08-06T22:08:22+0000"
        },
        {
            "bbclassextend": "",
            "blacklisted": "",
            "bugtracker": "",
            "description": "OpenWrt's micro bus architecture, similar to DBus; it contains a RPC DAEMON 'ubusd' and a command line utility tool 'ubus', the 'ubus' command line client allows to interact with the 'ubusd' rpc server.",
            "filename": "ubus_git.bb",
            "filepath": "recipes-core-luci/ubus",
            "homepage": "",
            "id": 682640,
            "inherits": "cmake systemd",
            "layerbranch": 833859,
            "license": "LGPLv2.1",
            "pn": "ubus",
            "provides": "ubus ",
            "pv": "git",
            "section": "console/utils",
            "summary": "OpenWrt's micro bus architecture",
            "updated": "2018-08-06T22:08:22+0000"
        },
        {
            "bbclassextend": "",
            "blacklisted": "",
            "bugtracker": "",
            "description": "",
            "filename": "firewall_3.0.bb",
            "filepath": "recipes-core-luci/firewall",
            "homepage": "",
            "id": 682641,
            "inherits": "cmake systemd",
            "layerbranch": 833859,
            "license": "GPLv2",
            "pn": "firewall",
            "provides": "firewall ",
            "pv": "3.0",
            "section": "console/utils",
            "summary": "",
            "updated": "2018-08-06T22:08:22+0000"
        },
        {
            "bbclassextend": "",
            "blacklisted": "",
            "bugtracker": "",
            "description": "netifd is an RPC-capable daemon written in C for better access to kernel APIs with the ability to listen on netlink events.",
            "filename": "netifd_git.bb",
            "filepath": "recipes-core-luci/netifd",
            "homepage": "",
            "id": 682642,
            "inherits": "cmake systemd update-alternatives",
            "layerbranch": 833859,
            "license": "GPLv2",
            "pn": "netifd",
            "provides": "netifd ",
            "pv": "git",
            "section": "console/utils",
            "summary": "OpenWrt Network Interface Configuration Daemon",
            "updated": "2018-08-06T22:08:22+0000"
        },
        {
            "bbclassextend": "",
            "blacklisted": "",
            "bugtracker": "",
            "description": "This package contains a stripped down version of libnl",
            "filename": "libnl-tiny_svn.bb",
            "filepath": "recipes-core-luci/libnl-tiny",
            "homepage": "",
            "id": 682643,
            "inherits": "",
            "layerbranch": 833859,
            "license": "GPLv2 & LGPLv2.1",
            "pn": "libnl-tiny",
            "provides": "libnl-tiny ",
            "pv": "svn",
            "section": "console/network",
            "summary": "netlink socket library",
            "updated": "2018-08-06T22:08:23+0000"
        },
        {
            "bbclassextend": "",
            "blacklisted": "",
            "bugtracker": "",
            "description": "\tMultiWan is a package name from openwrt, which provides agent script     that makes Multi-WAN configuration simple, easy and manageable. Complete with load     balancing, failover and an easy to manage traffic ruleset.         However, script here is a stripped version, just test connectivity, select one     as default, and swith to next one if fail.",
            "filename": "multiwan_1.1.0.bb",
            "filepath": "recipes-core-luci/multiwan",
            "homepage": "",
            "id": 682644,
            "inherits": "systemd",
            "layerbranch": 833859,
            "license": "windriver",
            "pn": "multiwan",
            "provides": "multiwan ",
            "pv": "1.1.0",
            "section": "console/utils",
            "summary": "",
            "updated": "2018-08-06T22:08:23+0000"
        },
        {
            "bbclassextend": "",
            "blacklisted": "",
            "bugtracker": "",
            "description": "This package provide GWP basic rootfs infrastructure support.",
            "filename": "gw-base_1.0.bb",
            "filepath": "recipes-core-luci/gw-base",
            "homepage": "",
            "id": 682645,
            "inherits": "systemd",
            "layerbranch": 833859,
            "license": "windriver",
            "pn": "gw-base",
            "provides": "gw-base ",
            "pv": "1.0",
            "section": "base",
            "summary": "",
            "updated": "2018-08-06T22:08:23+0000"
        },
        {
            "bbclassextend": "",
            "blacklisted": "",
            "bugtracker": "",
            "description": "",
            "filename": "fcgiwrap_1.1.0.bb",
            "filepath": "recipes-extended-luci/fcgiwrap",
            "homepage": "http://wiki.nginx.org/Fcgiwrap",
            "id": 682646,
            "inherits": "autotools pkgconfig siteconfig siteinfo systemd",
            "layerbranch": 833859,
            "license": "BSD",
            "pn": "fcgiwrap",
            "provides": "fcgiwrap ",
            "pv": "1.1.0",
            "section": "base",
            "summary": "",
            "updated": "2018-08-06T22:08:23+0000"
        },
        {
            "bbclassextend": "native",
            "blacklisted": "",
            "bugtracker": "",
            "description": "nodeJS Evented I/O for V8 JavaScript",
            "filename": "nodejs_0.10.35.bb",
            "filepath": "recipes-devtools/nodejs",
            "homepage": "http://nodejs.org",
            "id": 682647,
            "inherits": "",
            "layerbranch": 833859,
            "license": "MIT & BSD-2-Clause & BSD-3-Clause & ISC & AFL-2.0 & Apache-2.0 & OpenSSL & Zlib & Artistic-2.0 & (BSD-3-Clause | GPLv2)",
            "pn": "nodejs",
            "provides": "nodejs ",
            "pv": "0.10.35",
            "section": "base",
            "summary": "",
            "updated": "2018-08-06T22:08:23+0000"
        },
        {
            "bbclassextend": "native",
            "blacklisted": "",
            "bugtracker": "",
            "description": "nodeJS Evented I/O for V8 JavaScript",
            "filename": "nodejs_4.2.4.bb",
            "filepath": "recipes-devtools/nodejs",
            "homepage": "http://nodejs.org",
            "id": 682648,
            "inherits": "",
            "layerbranch": 833859,
            "license": "MIT & BSD-2-Clause & BSD-3-Clause & ISC & AFL-2.0 & Apache-2.0 & OpenSSL & Zlib & Artistic-2.0 & (BSD-3-Clause | GPLv2)",
            "pn": "nodejs",
            "provides": "nodejs ",
            "pv": "4.2.4",
            "section": "base",
            "summary": "",
            "updated": "2018-08-06T22:08:23+0000"
        },
        {
            "bbclassextend": "",
            "blacklisted": "",
            "bugtracker": "",
            "description": "",
            "filename": "cube-gw_0.1.bb",
            "filepath": "recipes-core/images",
            "homepage": "",
            "id": 682649,
            "inherits": "",
            "layerbranch": 833859,
            "license": "",
            "pn": "cube-gw",
            "provides": "",
            "pv": "",
            "section": "",
            "summary": "",
            "updated": "2018-08-06T22:08:23+0000"
        },
        {
            "bbclassextend": "",
            "blacklisted": "",
            "bugtracker": "",
            "description": "",
            "filename": "cube-gw-gfx_0.1.bb",
            "filepath": "recipes-core/images",
            "homepage": "",
            "id": 682650,
            "inherits": "",
            "layerbranch": 833859,
            "license": "",
            "pn": "cube-gw-gfx",
            "provides": "",
            "pv": "",
            "section": "",
            "summary": "",
            "updated": "2018-08-06T22:08:23+0000"
        },
        {
            "bbclassextend": "",
            "blacklisted": "",
            "bugtracker": "",
            "description": "Standard Web Interface including full admin features.",
            "filename": "luci_0.12.bb",
            "filepath": "recipes-luci/luci",
            "homepage": "",
            "id": 682651,
            "inherits": "",
            "layerbranch": 833859,
            "license": "GPLv2",
            "pn": "luci",
            "provides": "luci ",
            "pv": "0.12",
            "section": "webconsole",
            "summary": "LUCI Web Interface",
            "updated": "2018-08-06T22:08:23+0000"
        },
        {
            "bbclassextend": "",
            "blacklisted": "",
            "bugtracker": "",
            "description": "Command line frontend for the wireless information library.",
            "filename": "iwinfo_git.bb",
            "filepath": "recipes-luci/iwinfo",
            "homepage": "",
            "id": 682652,
            "inherits": "",
            "layerbranch": 833859,
            "license": "GPLv2",
            "pn": "iwinfo",
            "provides": "iwinfo ",
            "pv": "git",
            "section": "webconsole",
            "summary": "Wireless information library",
            "updated": "2018-08-06T22:08:24+0000"
        }
    ],
    "wrtemplates": [
        {
            "description": "",
            "id": 26901,
            "layerbranch": 833859,
            "name": "default",
            "updated": "2018-08-06T22:08:21+0000"
        }
    ]
}